[
    {
        "Series":"GOU25",
        "Contract Month":"U",
        "Open":"",
        "High":3752.5,
        "Low":3716.0,
        "Bid":3745.6,
        "Offer":3746.1,
        "Last":3746.0,
        "Chg (%Chg)":"18.7(0.5)",
        "Vol (Contract)":13799,
        "OI (Contract)":14730,
        "Prior SP":3727.3,
        "SP":null,
        "ExpiryDate":"2025-09-29",
        "Days Left":"",
        "MULTIPLER":300,
        "SPREAD":0.1,
        "UNDERLYING":"GO",
        "UNDERLYING PRICE":null,
        "THEORETICAL":0.0,
        "INTRINSIC VALUE":"",
        "MONEYNESS":"",
        "greekVOLATILITY":"",
        "MARKET NAME":"TXM",
        "IV BID":"",
        "IV LAST":"",
        "IV OFFER":"",
        "Diff":3746.0,
        "Premuim vs Discount":"Premium",
        "Suggest":"Short"
    },
    {
        "Series":"GOZ25",
        "Contract Month":"Z",
        "Open":"",
        "High":3797.4,
        "Low":3761.1,
        "Bid":3791.1,
        "Offer":3791.4,
        "Last":3791.4,
        "Chg (%Chg)":"18.6(0.49)",
        "Vol (Contract)":18667,
        "OI (Contract)":20470,
        "Prior SP":3772.8,
        "SP":null,
        "ExpiryDate":"2025-12-29",
        "Days Left":"",
        "MULTIPLER":300,
        "SPREAD":0.1,
        "UNDERLYING":"GO",
        "UNDERLYING PRICE":null,
        "THEORETICAL":0.0,
        "INTRINSIC VALUE":"",
        "MONEYNESS":"",
        "greekVOLATILITY":"",
        "MARKET NAME":"TXM",
        "IV BID":"",
        "IV LAST":"",
        "IV OFFER":"",
        "Diff":3791.4,
        "Premuim vs Discount":"Premium",
        "Suggest":"Short"
    }
]